LICENSE
MANIFEST.in
README.md
requirements.txt
setup.cfg
setup.py
docs/__init__.py
docs/conf.py
wiki/__init__.py
wiki/admin.py
wiki/managers.py
wiki/conf/__init__.py
wiki/conf/settings.py
wiki/core/__init__.py
wiki/core/compat.py
wiki/core/diff.py
wiki/core/exceptions.py
wiki/core/permissions.py
wiki/core/utils.py
wiki/locale/de/LC_MESSAGES/django.mo
wiki/locale/de/LC_MESSAGES/django.po
wiki/locale/es/LC_MESSAGES/django.mo
wiki/locale/es/LC_MESSAGES/django.po
wiki/locale/fr/LC_MESSAGES/django.mo
wiki/locale/fr/LC_MESSAGES/django.po
wiki/locale/pt_BR/LC_MESSAGES/django.mo
wiki/locale/pt_BR/LC_MESSAGES/django.po
wiki/locale/ru/LC_MESSAGES/django.mo
wiki/locale/ru/LC_MESSAGES/django.po
wiki/management/__init__.py
wiki/management/commands/__init__.py
wiki/management/commands/wikiviz.py
wiki/migrations/0001_initial.py
wiki/migrations/0002_auto__add_field_section_latest_revision.py
wiki/migrations/__init__.py
wiki/models/__init__.py
wiki/models/article.py
wiki/models/section.py
wiki/models/urlpath.py
wiki_base.egg-info/PKG-INFO
wiki_base.egg-info/SOURCES.txt
wiki_base.egg-info/dependency_links.txt
wiki_base.egg-info/not-zip-safe
wiki_base.egg-info/requires.txt
wiki_base.egg-info/top_level.txt