Metadata-Version: 1.1
Name: wiki-base
Version: 0.2.5
Summary: A collection of wiki-like Django modules for integration with APIs. Based on wiki package.
Home-page: http://github.com/skakri/django-wiki-base
Author: Kristaps Karlsons
Author-email: kristaps.karlsons@gmail.com
License: GPLv3
Keywords: django wiki markdown
Platform: UNKNOWN
Classifier: Development Status :: 3 - Alpha
Classifier: License :: OSI Approved :: GNU General Public License v3 (GPLv3)
Classifier: Environment :: Web Environment
Classifier: Framework :: Django
Classifier: Intended Audience :: Developers
Classifier: Operating System :: OS Independent
Classifier: Programming Language :: Python
Classifier: Topic :: Internet :: WWW/HTTP :: Dynamic Content
Classifier: Topic :: Software Development
Classifier: Topic :: Software Development :: Libraries :: Application Frameworks
